jupyter_app.py
jupyter_app-0.1.dist-info/entry_points.txt
jupyter_app-0.1.dist-info/LICENSE
jupyter_app-0.1.dist-info/WHEEL
jupyter_app-0.1.dist-info/METADATA
jupyter_app-0.1.dist-info/RECORD
