Metadata-Version: 1.2
Name: jupyter_app
Version: 0.1
Summary: jupyter_app - run Jupyter lab as a desktop app
Home-page: https://github.com/almarklein/jupyter_app
License: UNKNOWN
Author: Almar Klein
Author-email: almar.klein@gmail.com
Requires-Python: >=3.4
Classifier: Intended Audience :: Developers
Classifier: License :: OSI Approved :: BSD License
Classifier: Programming Language :: Python :: 3
Classifier: Topic :: Software Development :: Libraries :: Python Modules
Requires-Dist: jupyterlab
Requires-Dist: webruntime
Requires-Dist: dialite
